nngeometry/__init__.py
nngeometry/gram.py
nngeometry/hessian.py
nngeometry/jacobian.py
nngeometry/layercollection.py
nngeometry/layers.py
nngeometry/maths.py
nngeometry/metrics.py
nngeometry/utils.py
nngeometry/backend/__init__.py
nngeometry/backend/_backend.py
nngeometry/backend/dummy.py
nngeometry/backend/torch_func_hessian.py
nngeometry/backend/torch_hooks/__init__.py
nngeometry/backend/torch_hooks/grads.py
nngeometry/backend/torch_hooks/grads_conv.py
nngeometry/backend/torch_hooks/torch_hooks.py
nngeometry/object/__init__.py
nngeometry/object/fspace.py
nngeometry/object/map.py
nngeometry/object/pspace.py
nngeometry/object/vector.py
nngeometry-0.4.dist-info/METADATA
nngeometry-0.4.dist-info/WHEEL
nngeometry-0.4.dist-info/licenses/LICENSE
nngeometry-0.4.dist-info/RECORD
