Metadata-Version: 2.4
Name: nngeometry
Version: 0.4
Summary: {KFAC,EKFAC,Diagonal,Implicit} Fisher Matrices and finite width NTKs in PyTorch
Project-URL: Documentation, https://nngeometry.readthedocs.io/
Project-URL: Issues, https://github.com/tfjgeorge/nngeometry/issues
Project-URL: Source, https://github.com/tfjgeorge/nngeometry
Author-email: Thomas George <tfjgeorge@gmail.com>
License-Expression: BSD-3-Clause
License-File: LICENSE
Classifier: Intended Audience :: Developers
Classifier: Intended Audience :: Science/Research
Classifier: License :: OSI Approved :: BSD License
Classifier: Programming Language :: Python
Classifier: Programming Language :: Python :: 3
Classifier: Programming Language :: Python :: 3 :: Only
Classifier: Programming Language :: Python :: 3.9
Classifier: Programming Language :: Python :: 3.10
Classifier: Programming Language :: Python :: 3.11
Classifier: Programming Language :: Python :: 3.12
Classifier: Programming Language :: Python :: 3.13
Requires-Python: >=3.9
Requires-Dist: torch
Requires-Dist: torchvision
